odoo/addons/agreement_helpdesk_mgmt/README.rst
odoo/addons/agreement_helpdesk_mgmt/__init__.py
odoo/addons/agreement_helpdesk_mgmt/__manifest__.py
odoo/addons/agreement_helpdesk_mgmt/i18n/agreement_helpdesk_mgmt.pot
odoo/addons/agreement_helpdesk_mgmt/models/__init__.py
odoo/addons/agreement_helpdesk_mgmt/models/agreement.py
odoo/addons/agreement_helpdesk_mgmt/models/helpdesk_ticket.py
odoo/addons/agreement_helpdesk_mgmt/readme/CONTRIBUTORS.rst
odoo/addons/agreement_helpdesk_mgmt/readme/CREDITS.rst
odoo/addons/agreement_helpdesk_mgmt/readme/DESCRIPTION.rst
odoo/addons/agreement_helpdesk_mgmt/readme/USAGE.rst
odoo/addons/agreement_helpdesk_mgmt/static/description/banner.png
odoo/addons/agreement_helpdesk_mgmt/static/description/icon.png
odoo/addons/agreement_helpdesk_mgmt/static/description/index.html
odoo/addons/agreement_helpdesk_mgmt/tests/__init__.py
odoo/addons/agreement_helpdesk_mgmt/tests/test_agreement_helpdesk_mgmt.py
odoo/addons/agreement_helpdesk_mgmt/views/agreement.xml
odoo/addons/agreement_helpdesk_mgmt/views/helpdesk_ticket.xml
odoo12_addon_agreement_helpdesk_mgmt-12.0.1.0.2.dist-info/METADATA
odoo12_addon_agreement_helpdesk_mgmt-12.0.1.0.2.dist-info/WHEEL
odoo12_addon_agreement_helpdesk_mgmt-12.0.1.0.2.dist-info/top_level.txt
odoo12_addon_agreement_helpdesk_mgmt-12.0.1.0.2.dist-info/RECORD
